
<annotation>
	<folder></folder>
	<filename>1040.jpg</filename>
	<path>C:\Users\Anton\Projects\alpr_site_plates_segmentation/saved_cars2/1040.jpg</path>
	<source>
		<database>Unknown</database>
	</source>
	<size>
		<width>720</width>
		<height>1080</height>
		<depth>1</depth>
	</size>
	<segmented>0</segmented>
	<object>
		<name>car</name>
		<pose>Unspecified</pose>
		<truncated>0</truncated>
		<difficult>0</difficult>
		<bndbox>
			<xmin>256</xmin>
			<ymin>168</ymin>
			<xmax>424</xmax>
			<ymax>374</ymax>
		</bndbox>
	</object>
	<object>
		<name>car</name>
		<pose>Unspecified</pose>
		<truncated>0</truncated>
		<difficult>0</difficult>
		<bndbox>
			<xmin>723</xmin>
			<ymin>36</ymin>
			<xmax>973</xmax>
			<ymax>145</ymax>
		</bndbox>
	</object>
</annotation>