
<annotation>
	<folder></folder>
	<filename>1637.jpg</filename>
	<path>C:\Users\Anton\Projects\alpr_site_plates_segmentation/saved_cars2/1637.jpg</path>
	<source>
		<database>Unknown</database>
	</source>
	<size>
		<width>720</width>
		<height>1080</height>
		<depth>1</depth>
	</size>
	<segmented>0</segmented>
	<object>
		<name>car</name>
		<pose>Unspecified</pose>
		<truncated>0</truncated>
		<difficult>0</difficult>
		<bndbox>
			<xmin>907</xmin>
			<ymin>291</ymin>
			<xmax>1080</xmax>
			<ymax>450</ymax>
		</bndbox>
	</object>
	<object>
		<name>car</name>
		<pose>Unspecified</pose>
		<truncated>0</truncated>
		<difficult>0</difficult>
		<bndbox>
			<xmin>660</xmin>
			<ymin>182</ymin>
			<xmax>740</xmax>
			<ymax>230</ymax>
		</bndbox>
	</object>
	<object>
		<name>car</name>
		<pose>Unspecified</pose>
		<truncated>0</truncated>
		<difficult>0</difficult>
		<bndbox>
			<xmin>565</xmin>
			<ymin>113</ymin>
			<xmax>633</xmax>
			<ymax>194</ymax>
		</bndbox>
	</object>
	<object>
		<name>car</name>
		<pose>Unspecified</pose>
		<truncated>0</truncated>
		<difficult>0</difficult>
		<bndbox>
			<xmin>613</xmin>
			<ymin>107</ymin>
			<xmax>715</xmax>
			<ymax>181</ymax>
		</bndbox>
	</object>
</annotation>