
<annotation>
	<folder></folder>
	<filename>201.jpg</filename>
	<path>C:\Users\Anton\Projects\alpr_site_plates_segmentation/saved_cars2/201.jpg</path>
	<source>
		<database>Unknown</database>
	</source>
	<size>
		<width>720</width>
		<height>1080</height>
		<depth>1</depth>
	</size>
	<segmented>0</segmented>
	<object>
		<name>car</name>
		<pose>Unspecified</pose>
		<truncated>0</truncated>
		<difficult>0</difficult>
		<bndbox>
			<xmin>84</xmin>
			<ymin>684</ymin>
			<xmax>142</xmax>
			<ymax>720</ymax>
		</bndbox>
	</object>
	<object>
		<name>car</name>
		<pose>Unspecified</pose>
		<truncated>0</truncated>
		<difficult>0</difficult>
		<bndbox>
			<xmin>795</xmin>
			<ymin>18</ymin>
			<xmax>885</xmax>
			<ymax>37</ymax>
		</bndbox>
	</object>
</annotation>