
<annotation>
	<folder></folder>
	<filename>818.jpg</filename>
	<path>C:\Users\Anton\Projects\alpr_site_plates_segmentation/saved_cars2/818.jpg</path>
	<source>
		<database>Unknown</database>
	</source>
	<size>
		<width>720</width>
		<height>1080</height>
		<depth>1</depth>
	</size>
	<segmented>0</segmented>
	<object>
		<name>car</name>
		<pose>Unspecified</pose>
		<truncated>0</truncated>
		<difficult>0</difficult>
		<bndbox>
			<xmin>477</xmin>
			<ymin>493</ymin>
			<xmax>838</xmax>
			<ymax>720</ymax>
		</bndbox>
	</object>
	<object>
		<name>car</name>
		<pose>Unspecified</pose>
		<truncated>0</truncated>
		<difficult>0</difficult>
		<bndbox>
			<xmin>751</xmin>
			<ymin>112</ymin>
			<xmax>795</xmax>
			<ymax>145</ymax>
		</bndbox>
	</object>
	<object>
		<name>car</name>
		<pose>Unspecified</pose>
		<truncated>0</truncated>
		<difficult>0</difficult>
		<bndbox>
			<xmin>547</xmin>
			<ymin>73</ymin>
			<xmax>868</xmax>
			<ymax>335</ymax>
		</bndbox>
	</object>
</annotation>